omicron_utils/OmicronCondorJob.py
omicron_utils/TerminalFormat.py
omicron_utils/__init__.py
omicron_utils/_version.py
omicron_utils/check_certs.py
omicron_utils/conda_fns.py
omicron_utils/condor_utils.py
omicron_utils/config_utils.py
omicron_utils/histogram_plot.py
omicron_utils/ligoomicron.ini
omicron_utils/omicron_config.py
omicron_utils-0.0.17.dist-info/licenses/LICENSE
omicron_utils-0.0.17.dist-info/METADATA
omicron_utils-0.0.17.dist-info/WHEEL
omicron_utils-0.0.17.dist-info/entry_points.txt
omicron_utils-0.0.17.dist-info/top_level.txt
omicron_utils-0.0.17.dist-info/RECORD
