Metadata-Version: 2.4
Name: omicron_utils
Version: 0.0.17
Summary: Collection of common classes and function supporting LIGO Omicron pipelines
Author-email: Joseph Areeda <joseph.areeda@ligo.org>
Project-URL: Bug Tracker, https://git.ligo.org/joseph-areeda/omicron_utils/-/issues
Project-URL: Source Code, https://git.ligo.org/joseph-areeda/omicron_utils
Classifier: Development Status :: 4 - Beta
Classifier: Intended Audience :: Science/Research
Classifier: License :: OSI Approved :: GNU General Public License v3 or later (GPLv3+)
Classifier: Natural Language :: English
Classifier: Operating System :: OS Independent
Classifier: Programming Language :: Python
Classifier: Programming Language :: Python :: 3
Classifier: Programming Language :: Python :: 3.10
Classifier: Programming Language :: Python :: 3.11
Classifier: Topic :: Scientific/Engineering :: Astronomy
Classifier: Topic :: Scientific/Engineering :: Physics
Requires-Python: <3.12,>=3.10
License-File: LICENSE
Dynamic: license-file
